{
  "mapa_pg_id": "MAPA-PG-HISTOR",
  "sufixo": "HISTOR",
  "cd_programa_ies": "53001010011P5",
  "nome_programa": "HISTÓRIA",
  "graus": [
    "MESTRADO/DOUTORADO"
  ],
  "modalidade": [
    "ACADÊMICO"
  ],
  "conceito": [
    "4"
  ],
  "situacao": "EM FUNCIONAMENTO",
  "sigla_ies": "UNB",
  "nome_ies": "UNIVERSIDADE DE BRASÍLIA",
  "area_capes": "HISTÓRIA",
  "cd_area_capes": "40",
  "slug_area": "historia",
  "grande_area_cnpq": "CIÊNCIAS HUMANAS",
  "area_conhecimento": "HISTÓRIA",
  "area_basica": "HISTÓRIA",
  "sigaa_unb": "https://sigaa.unb.br/sigaa/public/curso/lista.jsf?nivel=S&aba=p-stricto",
  "capes_dataset": "https://dadosabertos.capes.gov.br/dataset",
  "gerado_em": "2026-05-05 20:27:16",
  "shell": "../../index.html?curso=HISTOR"
}