{"metadata":{"quadrienio":"2021-2024","anos":["2021","2022","2023","2024"],"dedup":"completa","n_nacional_declaracoes":13505,"n_nacional_distintas":8381,"cobertura_nacional":{"tit":100.0,"cod":95.1,"dep":96.2,"con":11.1,"res":22.1,"est":24.9},"campo_coletado":{"tit":true,"cod":true,"dep":true,"con":true,"res":true,"est":true},"area":"ECONOMIA","slug":"economia","subtipo":"PATENTE","n_programas":2,"n_declaracoes":8,"n_distintas":5,"gerado_em":"2026-07-21 18:58:38","fonte":"CAPES — Detalhes da Produção Intelectual Técnica + Produção Intelectual, 2021-2024"},"programas":{"25001019087P9":{"n":5,"ano":{"2021":0,"2022":1,"2023":4,"2024":0},"n_res":0,"n_cod":5,"n_dep":5,"n_con":0,"pat":[{"id":"39111024","ano":"2022","tit":"SISTEMA MAGNÉTICO PARA DETECÇÃO DE ANALITOS","cod":"BR10220090955","inst":"INPI - INSTITUTO NACIONAL DA PROPRIEDADE INDUSTRIAL","dep":"10/05/2022","lp":"AVALIAÇÃO"},{"id":"38123242","ano":"2023","tit":"HÍBRIDO IBPA: SÍNTESE, CARACTERIZAÇÃO E POTENCIAL TERAPÊUTICO","cod":"BR10202301427","inst":"INPI - INSTITUTO NACIONAL DA PROPRIEDADE INDUSTRIAL","dep":"16/07/2023","lp":"AVALIAÇÃO"},{"id":"38123260","ano":"2023","tit":"MODULO INTELIGENTE DE SEGURANCA INTEGRADA","cod":"BR1020230164366","inst":"INPI - INSTITUTO NACIONAL DA PROPRIEDADE INDUSTRIAL","dep":"16/08/2023","lp":"FINANCIAMENTO"},{"id":"38123261","ano":"2023","tit":"MODULO MULTIFUNCIONAL DE ATENDIMENTO INTERNO E EXTERNO - MMAIE","cod":"BR1020230163440","inst":"INPI - INSTITUTO NACIONAL DA PROPRIEDADE INDUSTRIAL","dep":"15/08/2023","lp":"FINANCIAMENTO"},{"id":"38123262","ano":"2023","tit":"MÓDULO MULTIFUNCIONAL DE SEGURANÇA INTEGRADA","cod":"BR1020230066119","inst":"INPI - INSTITUTO NACIONAL DA PROPRIEDADE INDUSTRIAL","dep":"10/04/2023","lp":"FINANCIAMENTO"}]},"25001019017P0":{"n":3,"ano":{"2021":0,"2022":0,"2023":3,"2024":0},"n_res":0,"n_cod":3,"n_dep":3,"n_con":0,"pat":[{"id":"38694094","ano":"2023","tit":"MODULO INTELIGENTE DE SEGURANCA INTEGRADA","cod":"BR1020230164366","inst":"INPI - INSTITUTO NACIONAL DA PROPRIEDADE INDUSTRIAL","dep":"16/08/2023"},{"id":"38694097","ano":"2023","tit":"MODULO MULTIFUNCIONAL DE ATENDIMENTO INTERNO E EXTERNO - MMAIE","cod":"BR1020230163440","inst":"INPI - INSTITUTO NACIONAL DA PROPRIEDADE INDUSTRIAL","dep":"15/08/2023"},{"id":"38694100","ano":"2023","tit":"MÓDULO MULTIFUNCIONAL DE SEGURANÇA INTEGRADA","cod":"BR1020230066119","inst":"INPI - INSTITUTO NACIONAL DA PROPRIEDADE INDUSTRIAL","dep":"10/04/2023"}]}}}